{"stats":{"minecraft:picked_up":{"minecraft:slime_ball":2,"minecraft:green_concrete_powder":2,"minecraft:wheat_seeds":1,"minecraft:bamboo":13,"minecraft:prismarine_crystals":4,"minecraft:dirt":3,"minecraft:cobblestone":287},"minecraft:dropped":{"minecraft:wheat_seeds":1},"minecraft:custom":{"minecraft:open_chest":20,"minecraft:time_since_rest":12653,"minecraft:play_one_minute":245303,"minecraft:crouch_one_cm":631,"minecraft:damage_taken":5349,"minecraft:sprint_one_cm":152100,"minecraft:open_enderchest":2,"minecraft:walk_one_cm":142696,"minecraft:deaths":19,"minecraft:sneak_time":344,"minecraft:walk_under_water_one_cm":5310,"minecraft:mob_kills":2,"minecraft:drop":1,"minecraft:jump":1037,"minecraft:minecart_one_cm":27188,"minecraft:damage_dealt":521,"minecraft:leave_game":90,"minecraft:time_since_death":12651,"minecraft:walk_on_water_one_cm":9625,"minecraft:climb_one_cm":5809,"minecraft:damage_resisted":56,"minecraft:swim_one_cm":1998,"minecraft:fall_one_cm":33962,"minecraft:fly_one_cm":512700},"minecraft:mined":{"minecraft:grass":5,"minecraft:grass_block":2,"minecraft:green_concrete_powder":1,"minecraft:dirt":1,"minecraft:tall_grass":1,"minecraft:spruce_leaves":1,"minecraft:sea_lantern":1},"minecraft:killed_by":{"minecraft:husk":3,"minecraft:skeleton":4,"minecraft:zombie_villager":1,"minecraft:spider":1,"minecraft:zombie":3,"minecraft:pillager":1},"minecraft:used":{"minecraft:beef":2},"minecraft:killed":{"minecraft:zombie":1,"minecraft:slime":1}},"DataVersion":2578}